[
    {
        "question": "Könyv",
        "answers": [ "Bag", "Baloon", "Book", "Cake", "Car", "Cat", "Dog", "Guitar", "Hairbrush", "Hat", "Jumper", "Pen", "Pencil", "Pencilcase", "Shoes", "Socks", "T-shirt", "Toothbrush", "Towel", "Train" ],
        "correctAnswer": "Book"
    },
    {
        "question": "Pulóver",
        "answers": [ "Bag", "Baloon", "Book", "Cake", "Car", "Cat", "Dog", "Guitar", "Hairbrush", "Hat", "Jumper", "Pen", "Pencil", "Pencilcase", "Shoes", "Socks", "T-shirt", "Toothbrush", "Towel", "Train" ],
        "correctAnswer": "Jumper"
    },
    {
        "question": "Ceruza",
        "answers": [ "Bag", "Baloon", "Book", "Cake", "Car", "Cat", "Dog", "Guitar", "Hairbrush", "Hat", "Jumper", "Pen", "Pencil", "Pencilcase", "Shoes", "Socks", "T-shirt", "Toothbrush", "Towel", "Train" ],
        "correctAnswer": "Pencil"
    },
    {
        "question": "Autó",
        "answers": [ "Bag", "Baloon", "Book", "Cake", "Car", "Cat", "Dog", "Guitar", "Hairbrush", "Hat", "Jumper", "Pen", "Pencil", "Pencilcase", "Shoes", "Socks", "T-shirt", "Toothbrush", "Towel", "Train" ],
        "correctAnswer": "Car"
    }

]